TuGraphClient.py
setup.py
TuGraphClient.egg-info/PKG-INFO
TuGraphClient.egg-info/SOURCES.txt
TuGraphClient.egg-info/dependency_links.txt
TuGraphClient.egg-info/requires.txt
TuGraphClient.egg-info/top_level.txt