Metadata-Version: 1.0
Name: TuGraphClient
Version: 2.0
Summary: rest client for TuGraph
Home-page: UNKNOWN
Author: UNKNOWN
Author-email: UNKNOWN
License: UNKNOWN
Platform: UNKNOWN
